[
  {
    "symbol": "PTT",
    "name": "PTT",
    "price": 31.85,
    "change_24h": -2.01,
    "volume_24h": 20982354,
    "high_24h": 32.32,
    "low_24h": 31.37,
    "rsi": 43.87,
    "macd": {
      "macd": -0.1214,
      "signal": -0.0182,
      "histogram": -0.1032
    },
    "signal": "HOLD",
    "strength": 0.32,
    "sector": "Energy",
    "timestamp": "2026-01-10T19:44:45.486851Z"
  },
  {
    "symbol": "AOT",
    "name": "AOT",
    "price": 62.66,
    "change_24h": 1.07,
    "volume_24h": 13245799,
    "high_24h": 63.6,
    "low_24h": 61.72,
    "rsi": 57.04,
    "macd": {
      "macd": -0.0517,
      "signal": -0.0078,
      "histogram": -0.0439
    },
    "signal": "HOLD",
    "strength": 0.25,
    "sector": "Transport",
    "timestamp": "2026-01-10T19:44:45.486897Z"
  },
  {
    "symbol": "ADVANC",
    "name": "ADVANC",
    "price": 265.84,
    "change_24h": -0.8,
    "volume_24h": 995150,
    "high_24h": 269.83,
    "low_24h": 261.86,
    "rsi": 53.67,
    "macd": {
      "macd": -0.9358,
      "signal": -0.1404,
      "histogram": -0.7955
    },
    "signal": "HOLD",
    "strength": 0.15,
    "sector": "Telecom",
    "timestamp": "2026-01-10T19:44:45.486925Z"
  },
  {
    "symbol": "CPALL",
    "name": "CPALL",
    "price": 55.75,
    "change_24h": -0.88,
    "volume_24h": 13195578,
    "high_24h": 56.59,
    "low_24h": 54.92,
    "rsi": 43.84,
    "macd": {
      "macd": -0.1643,
      "signal": -0.0246,
      "histogram": -0.1397
    },
    "signal": "HOLD",
    "strength": 0.21,
    "sector": "Commerce",
    "timestamp": "2026-01-10T19:44:45.486947Z"
  },
  {
    "symbol": "SCC",
    "name": "SCC",
    "price": 361.67,
    "change_24h": 0.46,
    "volume_24h": 2410682,
    "high_24h": 367.09,
    "low_24h": 356.24,
    "rsi": 49.48,
    "macd": {
      "macd": 0.996,
      "signal": 0.1494,
      "histogram": 0.8466
    },
    "signal": "HOLD",
    "strength": 0.06,
    "sector": "Construction",
    "timestamp": "2026-01-10T19:44:45.486967Z"
  },
  {
    "symbol": "KBANK",
    "name": "KBANK",
    "price": 152.9,
    "change_24h": 0.26,
    "volume_24h": 3492255,
    "high_24h": 155.19,
    "low_24h": 150.61,
    "rsi": 46.33,
    "macd": {
      "macd": -0.0973,
      "signal": -0.0146,
      "histogram": -0.0827
    },
    "signal": "HOLD",
    "strength": 0.1,
    "sector": "Banking",
    "timestamp": "2026-01-10T19:44:45.486988Z"
  },
  {
    "symbol": "SCB",
    "name": "SCB",
    "price": 90.93,
    "change_24h": -5.03,
    "volume_24h": 5453989,
    "high_24h": 92.29,
    "low_24h": 89.57,
    "rsi": 35.59,
    "macd": {
      "macd": -0.2736,
      "signal": -0.041,
      "histogram": -0.2326
    },
    "signal": "HOLD",
    "strength": 0.79,
    "sector": "Banking",
    "timestamp": "2026-01-10T19:44:45.487008Z"
  },
  {
    "symbol": "BBL",
    "name": "BBL",
    "price": 175.06,
    "change_24h": 3.9,
    "volume_24h": 2031820,
    "high_24h": 177.69,
    "low_24h": 172.44,
    "rsi": 53.86,
    "macd": {
      "macd": 0.7941,
      "signal": 0.1191,
      "histogram": 0.675
    },
    "signal": "BUY",
    "strength": 0.47,
    "sector": "Banking",
    "timestamp": "2026-01-10T19:44:45.487030Z"
  },
  {
    "symbol": "GULF",
    "name": "GULF",
    "price": 46.41,
    "change_24h": 2.56,
    "volume_24h": 11655733,
    "high_24h": 47.11,
    "low_24h": 45.71,
    "rsi": 51.81,
    "macd": {
      "macd": 0.2669,
      "signal": 0.04,
      "histogram": 0.2268
    },
    "signal": "HOLD",
    "strength": 0.29,
    "sector": "Energy",
    "timestamp": "2026-01-10T19:44:45.487051Z"
  },
  {
    "symbol": "PTTEP",
    "name": "PTTEP",
    "price": 128.05,
    "change_24h": -5.15,
    "volume_24h": 5759769,
    "high_24h": 129.97,
    "low_24h": 126.13,
    "rsi": 42.81,
    "macd": {
      "macd": -0.8621,
      "signal": -0.1293,
      "histogram": -0.7328
    },
    "signal": "SELL",
    "strength": 0.66,
    "sector": "Energy",
    "timestamp": "2026-01-10T19:44:45.487071Z"
  },
  {
    "symbol": "BDMS",
    "name": "BDMS",
    "price": 28.91,
    "change_24h": 0.56,
    "volume_24h": 17507031,
    "high_24h": 29.35,
    "low_24h": 28.48,
    "rsi": 51.18,
    "macd": {
      "macd": -0.0548,
      "signal": -0.0082,
      "histogram": -0.0466
    },
    "signal": "HOLD",
    "strength": 0.08,
    "sector": "Healthcare",
    "timestamp": "2026-01-10T19:44:45.487091Z"
  },
  {
    "symbol": "TRUE",
    "name": "TRUE",
    "price": 10.53,
    "change_24h": 2.27,
    "volume_24h": 39401682,
    "high_24h": 10.69,
    "low_24h": 10.38,
    "rsi": 52.46,
    "macd": {
      "macd": 0.02,
      "signal": 0.003,
      "histogram": 0.017
    },
    "signal": "HOLD",
    "strength": 0.28,
    "sector": "Telecom",
    "timestamp": "2026-01-10T19:44:45.487113Z"
  },
  {
    "symbol": "BEM",
    "name": "BEM",
    "price": 8.65,
    "change_24h": 1.12,
    "volume_24h": 29624269,
    "high_24h": 8.78,
    "low_24h": 8.52,
    "rsi": 53.86,
    "macd": {
      "macd": 0.0033,
      "signal": 0.0005,
      "histogram": 0.0028
    },
    "signal": "HOLD",
    "strength": 0.19,
    "sector": "Transport",
    "timestamp": "2026-01-10T19:44:45.487133Z"
  },
  {
    "symbol": "MINT",
    "name": "MINT",
    "price": 32.65,
    "change_24h": 2.04,
    "volume_24h": 18696000,
    "high_24h": 33.14,
    "low_24h": 32.16,
    "rsi": 53.74,
    "macd": {
      "macd": -0.0321,
      "signal": -0.0048,
      "histogram": -0.0273
    },
    "signal": "HOLD",
    "strength": 0.28,
    "sector": "Food",
    "timestamp": "2026-01-10T19:44:45.487153Z"
  },
  {
    "symbol": "CPN",
    "name": "CPN",
    "price": 60.43,
    "change_24h": 3.3,
    "volume_24h": 12217974,
    "high_24h": 61.34,
    "low_24h": 59.53,
    "rsi": 59.24,
    "macd": {
      "macd": 0.1304,
      "signal": 0.0196,
      "histogram": 0.1108
    },
    "signal": "BUY",
    "strength": 0.52,
    "sector": "Property",
    "timestamp": "2026-01-10T19:44:45.487172Z"
  },
  {
    "symbol": "DELTA",
    "name": "DELTA",
    "price": 91.36,
    "change_24h": 2.36,
    "volume_24h": 3722789,
    "high_24h": 92.73,
    "low_24h": 89.99,
    "rsi": 50.51,
    "macd": {
      "macd": -0.2852,
      "signal": -0.0428,
      "histogram": -0.2425
    },
    "signal": "HOLD",
    "strength": 0.25,
    "sector": "Electronics",
    "timestamp": "2026-01-10T19:44:45.487193Z"
  },
  {
    "symbol": "EA",
    "name": "EA",
    "price": 18.47,
    "change_24h": -1.23,
    "volume_24h": 37607530,
    "high_24h": 18.75,
    "low_24h": 18.19,
    "rsi": 43.93,
    "macd": {
      "macd": 0.0165,
      "signal": 0.0025,
      "histogram": 0.014
    },
    "signal": "HOLD",
    "strength": 0.24,
    "sector": "Energy",
    "timestamp": "2026-01-10T19:44:45.487212Z"
  },
  {
    "symbol": "GPSC",
    "name": "GPSC",
    "price": 58.84,
    "change_24h": 1.45,
    "volume_24h": 5463805,
    "high_24h": 59.72,
    "low_24h": 57.96,
    "rsi": 55.4,
    "macd": {
      "macd": 0.2858,
      "signal": 0.0429,
      "histogram": 0.2429
    },
    "signal": "HOLD",
    "strength": 0.25,
    "sector": "Energy",
    "timestamp": "2026-01-10T19:44:45.487230Z"
  },
  {
    "symbol": "INTUCH",
    "name": "INTUCH",
    "price": 81.81,
    "change_24h": -3.76,
    "volume_24h": 6092595,
    "high_24h": 83.03,
    "low_24h": 80.58,
    "rsi": 42.23,
    "macd": {
      "macd": -0.2871,
      "signal": -0.0431,
      "histogram": -0.244
    },
    "signal": "SELL",
    "strength": 0.53,
    "sector": "Telecom",
    "timestamp": "2026-01-10T19:44:45.487249Z"
  },
  {
    "symbol": "IVL",
    "name": "IVL",
    "price": 31.03,
    "change_24h": -3.78,
    "volume_24h": 25419302,
    "high_24h": 31.5,
    "low_24h": 30.56,
    "rsi": 47.49,
    "macd": {
      "macd": -0.0883,
      "signal": -0.0132,
      "histogram": -0.0751
    },
    "signal": "SELL",
    "strength": 0.43,
    "sector": "Petrochemical",
    "timestamp": "2026-01-10T19:44:45.487269Z"
  },
  {
    "symbol": "KCE",
    "name": "KCE",
    "price": 42.79,
    "change_24h": -4.92,
    "volume_24h": 5739498,
    "high_24h": 43.43,
    "low_24h": 42.14,
    "rsi": 46.09,
    "macd": {
      "macd": -0.1854,
      "signal": -0.0278,
      "histogram": -0.1576
    },
    "signal": "SELL",
    "strength": 0.57,
    "sector": "Electronics",
    "timestamp": "2026-01-10T19:44:45.487287Z"
  },
  {
    "symbol": "KTB",
    "name": "KTB",
    "price": 22.6,
    "change_24h": -0.89,
    "volume_24h": 13896462,
    "high_24h": 22.94,
    "low_24h": 22.26,
    "rsi": 49.01,
    "macd": {
      "macd": 0.0466,
      "signal": 0.007,
      "histogram": 0.0396
    },
    "signal": "HOLD",
    "strength": 0.11,
    "sector": "Banking",
    "timestamp": "2026-01-10T19:44:45.487306Z"
  },
  {
    "symbol": "BANPU",
    "name": "BANPU",
    "price": 7.97,
    "change_24h": -3.39,
    "volume_24h": 68291226,
    "high_24h": 8.09,
    "low_24h": 7.85,
    "rsi": 43.89,
    "macd": {
      "macd": -0.0117,
      "signal": -0.0018,
      "histogram": -0.0099
    },
    "signal": "SELL",
    "strength": 0.46,
    "sector": "Energy",
    "timestamp": "2026-01-10T19:44:45.487325Z"
  },
  {
    "symbol": "BCP",
    "name": "BCP",
    "price": 26.78,
    "change_24h": -4.35,
    "volume_24h": 29731552,
    "high_24h": 27.18,
    "low_24h": 26.38,
    "rsi": 42.9,
    "macd": {
      "macd": -0.226,
      "signal": -0.0339,
      "histogram": -0.1921
    },
    "signal": "SELL",
    "strength": 0.58,
    "sector": "Energy",
    "timestamp": "2026-01-10T19:44:45.487343Z"
  },
  {
    "symbol": "BH",
    "name": "BH",
    "price": 151.6,
    "change_24h": 4.55,
    "volume_24h": 4278765,
    "high_24h": 153.87,
    "low_24h": 149.32,
    "rsi": 61.61,
    "macd": {
      "macd": 0.8418,
      "signal": 0.1263,
      "histogram": 0.7155
    },
    "signal": "HOLD",
    "strength": 0.69,
    "sector": "Healthcare",
    "timestamp": "2026-01-10T19:44:45.487362Z"
  },
  {
    "symbol": "BJC",
    "name": "BJC",
    "price": 32.92,
    "change_24h": 4.5,
    "volume_24h": 29567358,
    "high_24h": 33.41,
    "low_24h": 32.43,
    "rsi": 55.36,
    "macd": {
      "macd": 0.1948,
      "signal": 0.0292,
      "histogram": 0.1655
    },
    "signal": "BUY",
    "strength": 0.56,
    "sector": "Commerce",
    "timestamp": "2026-01-10T19:44:45.487381Z"
  },
  {
    "symbol": "BTS",
    "name": "BTS",
    "price": 6.57,
    "change_24h": 4.36,
    "volume_24h": 137047090,
    "high_24h": 6.67,
    "low_24h": 6.48,
    "rsi": 59.99,
    "macd": {
      "macd": -0.0007,
      "signal": -0.0001,
      "histogram": -0.0006
    },
    "signal": "HOLD",
    "strength": 0.64,
    "sector": "Transport",
    "timestamp": "2026-01-10T19:44:45.487399Z"
  },
  {
    "symbol": "CBG",
    "name": "CBG",
    "price": 132.46,
    "change_24h": 3.08,
    "volume_24h": 6361340,
    "high_24h": 134.45,
    "low_24h": 130.47,
    "rsi": 59.13,
    "macd": {
      "macd": 0.4138,
      "signal": 0.0621,
      "histogram": 0.3518
    },
    "signal": "BUY",
    "strength": 0.49,
    "sector": "Food",
    "timestamp": "2026-01-10T19:44:45.487418Z"
  },
  {
    "symbol": "CENTEL",
    "name": "CENTEL",
    "price": 37.73,
    "change_24h": -2.01,
    "volume_24h": 18830735,
    "high_24h": 38.29,
    "low_24h": 37.16,
    "rsi": 48.92,
    "macd": {
      "macd": -0.1144,
      "signal": -0.0172,
      "histogram": -0.0972
    },
    "signal": "HOLD",
    "strength": 0.22,
    "sector": "Hotel",
    "timestamp": "2026-01-10T19:44:45.487439Z"
  },
  {
    "symbol": "COM7",
    "name": "COM7",
    "price": 28.45,
    "change_24h": -1.04,
    "volume_24h": 19995941,
    "high_24h": 28.88,
    "low_24h": 28.02,
    "rsi": 44.79,
    "macd": {
      "macd": 0.0442,
      "signal": 0.0066,
      "histogram": 0.0376
    },
    "signal": "HOLD",
    "strength": 0.21,
    "sector": "Commerce",
    "timestamp": "2026-01-10T19:44:45.487459Z"
  },
  {
    "symbol": "CRC",
    "name": "CRC",
    "price": 34.38,
    "change_24h": -1.77,
    "volume_24h": 28411337,
    "high_24h": 34.9,
    "low_24h": 33.87,
    "rsi": 42.81,
    "macd": {
      "macd": -0.0125,
      "signal": -0.0019,
      "histogram": -0.0106
    },
    "signal": "HOLD",
    "strength": 0.32,
    "sector": "Commerce",
    "timestamp": "2026-01-10T19:44:45.487478Z"
  },
  {
    "symbol": "EGCO",
    "name": "EGCO",
    "price": 159.27,
    "change_24h": 0.81,
    "volume_24h": 5554732,
    "high_24h": 161.66,
    "low_24h": 156.88,
    "rsi": 55.19,
    "macd": {
      "macd": -0.321,
      "signal": -0.0481,
      "histogram": -0.2728
    },
    "signal": "HOLD",
    "strength": 0.18,
    "sector": "Energy",
    "timestamp": "2026-01-10T19:44:45.487497Z"
  },
  {
    "symbol": "GLOBAL",
    "name": "GLOBAL",
    "price": 18.68,
    "change_24h": 2.61,
    "volume_24h": 44003998,
    "high_24h": 18.96,
    "low_24h": 18.4,
    "rsi": 57.74,
    "macd": {
      "macd": 0.1006,
      "signal": 0.0151,
      "histogram": 0.0855
    },
    "signal": "HOLD",
    "strength": 0.42,
    "sector": "Food",
    "timestamp": "2026-01-10T19:44:45.487515Z"
  },
  {
    "symbol": "HMPRO",
    "name": "HMPRO",
    "price": 14.12,
    "change_24h": -3.28,
    "volume_24h": 33731486,
    "high_24h": 14.33,
    "low_24h": 13.91,
    "rsi": 40.36,
    "macd": {
      "macd": -0.0046,
      "signal": -0.0007,
      "histogram": -0.0039
    },
    "signal": "SELL",
    "strength": 0.52,
    "sector": "Commerce",
    "timestamp": "2026-01-10T19:44:45.487534Z"
  },
  {
    "symbol": "IRPC",
    "name": "IRPC",
    "price": 3.3,
    "change_24h": -3.37,
    "volume_24h": 281758298,
    "high_24h": 3.35,
    "low_24h": 3.26,
    "rsi": 45.9,
    "macd": {
      "macd": -0.0162,
      "signal": -0.0024,
      "histogram": -0.0138
    },
    "signal": "SELL",
    "strength": 0.42,
    "sector": "Petrochemical",
    "timestamp": "2026-01-10T19:44:45.487553Z"
  },
  {
    "symbol": "JMT",
    "name": "JMT",
    "price": 22.43,
    "change_24h": 1.49,
    "volume_24h": 38715011,
    "high_24h": 22.76,
    "low_24h": 22.09,
    "rsi": 56.39,
    "macd": {
      "macd": -0.0229,
      "signal": -0.0034,
      "histogram": -0.0194
    },
    "signal": "HOLD",
    "strength": 0.28,
    "sector": "Finance",
    "timestamp": "2026-01-10T19:44:45.487583Z"
  },
  {
    "symbol": "JMART",
    "name": "JMART",
    "price": 16.44,
    "change_24h": 4.02,
    "volume_24h": 40775624,
    "high_24h": 16.68,
    "low_24h": 16.19,
    "rsi": 54.68,
    "macd": {
      "macd": 0.0522,
      "signal": 0.0078,
      "histogram": 0.0444
    },
    "signal": "BUY",
    "strength": 0.5,
    "sector": "Commerce",
    "timestamp": "2026-01-10T19:44:45.487619Z"
  },
  {
    "symbol": "TIDLOR",
    "name": "TIDLOR",
    "price": 18.89,
    "change_24h": 2.1,
    "volume_24h": 52993159,
    "high_24h": 19.17,
    "low_24h": 18.6,
    "rsi": 59.61,
    "macd": {
      "macd": 0.0776,
      "signal": 0.0116,
      "histogram": 0.066
    },
    "signal": "HOLD",
    "strength": 0.4,
    "sector": "Finance",
    "timestamp": "2026-01-10T19:44:45.487650Z"
  },
  {
    "symbol": "TTB",
    "name": "TTB",
    "price": 1.81,
    "change_24h": 1.55,
    "volume_24h": 434710368,
    "high_24h": 1.83,
    "low_24h": 1.78,
    "rsi": 48.91,
    "macd": {
      "macd": 0.0058,
      "signal": 0.0009,
      "histogram": 0.005
    },
    "signal": "HOLD",
    "strength": 0.18,
    "sector": "Banking",
    "timestamp": "2026-01-10T19:44:45.487680Z"
  },
  {
    "symbol": "TU",
    "name": "TU",
    "price": 14.33,
    "change_24h": -4.44,
    "volume_24h": 66020344,
    "high_24h": 14.55,
    "low_24h": 14.12,
    "rsi": 43.72,
    "macd": {
      "macd": -0.0288,
      "signal": -0.0043,
      "histogram": -0.0245
    },
    "signal": "SELL",
    "strength": 0.57,
    "sector": "Food",
    "timestamp": "2026-01-10T19:44:45.487708Z"
  },
  {
    "symbol": "WHA",
    "name": "WHA",
    "price": 4.46,
    "change_24h": -2.13,
    "volume_24h": 103008763,
    "high_24h": 4.53,
    "low_24h": 4.4,
    "rsi": 43.02,
    "macd": {
      "macd": 0.0028,
      "signal": 0.0004,
      "histogram": 0.0024
    },
    "signal": "HOLD",
    "strength": 0.35,
    "sector": "Property",
    "timestamp": "2026-01-10T19:44:45.487727Z"
  },
  {
    "symbol": "OR",
    "name": "OR",
    "price": 18.7,
    "change_24h": 2.16,
    "volume_24h": 43954641,
    "high_24h": 18.98,
    "low_24h": 18.42,
    "rsi": 54.49,
    "macd": {
      "macd": 0.0214,
      "signal": 0.0032,
      "histogram": 0.0182
    },
    "signal": "HOLD",
    "strength": 0.31,
    "sector": "Energy",
    "timestamp": "2026-01-10T19:44:45.487746Z"
  },
  {
    "symbol": "AWC",
    "name": "AWC",
    "price": 4.98,
    "change_24h": 3.41,
    "volume_24h": 165667802,
    "high_24h": 5.06,
    "low_24h": 4.91,
    "rsi": 55.58,
    "macd": {
      "macd": 0.0305,
      "signal": 0.0046,
      "histogram": 0.026
    },
    "signal": "BUY",
    "strength": 0.45,
    "sector": "Property",
    "timestamp": "2026-01-10T19:44:45.487764Z"
  },
  {
    "symbol": "OSP",
    "name": "OSP",
    "price": 23.75,
    "change_24h": -3.08,
    "volume_24h": 20982508,
    "high_24h": 24.1,
    "low_24h": 23.39,
    "rsi": 36.86,
    "macd": {
      "macd": -0.0821,
      "signal": -0.0123,
      "histogram": -0.0698
    },
    "signal": "HOLD",
    "strength": 0.57,
    "sector": "Commerce",
    "timestamp": "2026-01-10T19:44:45.487782Z"
  },
  {
    "symbol": "SAWAD",
    "name": "SAWAD",
    "price": 41.1,
    "change_24h": -2.72,
    "volume_24h": 12019760,
    "high_24h": 41.72,
    "low_24h": 40.48,
    "rsi": 47.15,
    "macd": {
      "macd": -0.019,
      "signal": -0.0029,
      "histogram": -0.0162
    },
    "signal": "HOLD",
    "strength": 0.33,
    "sector": "Finance",
    "timestamp": "2026-01-10T19:44:45.487808Z"
  },
  {
    "symbol": "STGT",
    "name": "STGT",
    "price": 11.71,
    "change_24h": 4.58,
    "volume_24h": 75665250,
    "high_24h": 11.89,
    "low_24h": 11.54,
    "rsi": 52.77,
    "macd": {
      "macd": 0.0532,
      "signal": 0.008,
      "histogram": 0.0452
    },
    "signal": "BUY",
    "strength": 0.51,
    "sector": "Rubber",
    "timestamp": "2026-01-10T19:44:45.487841Z"
  },
  {
    "symbol": "TISCO",
    "name": "TISCO",
    "price": 102.51,
    "change_24h": 4.07,
    "volume_24h": 8682603,
    "high_24h": 104.05,
    "low_24h": 100.98,
    "rsi": 54.83,
    "macd": {
      "macd": 0.3087,
      "signal": 0.0463,
      "histogram": 0.2624
    },
    "signal": "BUY",
    "strength": 0.5,
    "sector": "Banking",
    "timestamp": "2026-01-10T19:44:45.487877Z"
  },
  {
    "symbol": "TOP",
    "name": "TOP",
    "price": 44.2,
    "change_24h": 3.39,
    "volume_24h": 14585379,
    "high_24h": 44.86,
    "low_24h": 43.54,
    "rsi": 51.83,
    "macd": {
      "macd": -0.0692,
      "signal": -0.0104,
      "histogram": -0.0588
    },
    "signal": "HOLD",
    "strength": 0.38,
    "sector": "Energy",
    "timestamp": "2026-01-10T19:44:45.487930Z"
  },
  {
    "symbol": "MTC",
    "name": "MTC",
    "price": 41.66,
    "change_24h": -0.8,
    "volume_24h": 16492485,
    "high_24h": 42.29,
    "low_24h": 41.04,
    "rsi": 48.48,
    "macd": {
      "macd": -0.2742,
      "signal": -0.0411,
      "histogram": -0.2331
    },
    "signal": "HOLD",
    "strength": 0.11,
    "sector": "Finance",
    "timestamp": "2026-01-10T19:44:45.487963Z"
  }
]