[
  {
    "symbol": "PTT",
    "name": "PTT",
    "price": 32.88,
    "change_24h": 1.16,
    "volume_24h": 14014228,
    "high_24h": 33.37,
    "low_24h": 32.38,
    "rsi": 46.98,
    "macd": {
      "macd": 0.0245,
      "signal": 0.0037,
      "histogram": 0.0208
    },
    "signal": "HOLD",
    "strength": 0.18,
    "sector": "Energy",
    "timestamp": "2026-01-05T15:12:24.489023Z"
  },
  {
    "symbol": "AOT",
    "name": "AOT",
    "price": 63.88,
    "change_24h": 3.03,
    "volume_24h": 7289293,
    "high_24h": 64.84,
    "low_24h": 62.92,
    "rsi": 52.9,
    "macd": {
      "macd": 0.1803,
      "signal": 0.0271,
      "histogram": 0.1533
    },
    "signal": "BUY",
    "strength": 0.36,
    "sector": "Transport",
    "timestamp": "2026-01-05T15:12:24.489068Z"
  },
  {
    "symbol": "ADVANC",
    "name": "ADVANC",
    "price": 255.26,
    "change_24h": -4.76,
    "volume_24h": 3123401,
    "high_24h": 259.08,
    "low_24h": 251.43,
    "rsi": 43.99,
    "macd": {
      "macd": 0.1878,
      "signal": 0.0282,
      "histogram": 0.1596
    },
    "signal": "HOLD",
    "strength": 0.6,
    "sector": "Telecom",
    "timestamp": "2026-01-05T15:12:24.489115Z"
  },
  {
    "symbol": "CPALL",
    "name": "CPALL",
    "price": 53.46,
    "change_24h": -4.96,
    "volume_24h": 7272219,
    "high_24h": 54.26,
    "low_24h": 52.66,
    "rsi": 43.73,
    "macd": {
      "macd": -0.2329,
      "signal": -0.0349,
      "histogram": -0.198
    },
    "signal": "SELL",
    "strength": 0.62,
    "sector": "Commerce",
    "timestamp": "2026-01-05T15:12:24.489154Z"
  },
  {
    "symbol": "SCC",
    "name": "SCC",
    "price": 364.38,
    "change_24h": 1.22,
    "volume_24h": 1360297,
    "high_24h": 369.85,
    "low_24h": 358.91,
    "rsi": 57.98,
    "macd": {
      "macd": 0.4419,
      "signal": 0.0663,
      "histogram": 0.3756
    },
    "signal": "HOLD",
    "strength": 0.28,
    "sector": "Construction",
    "timestamp": "2026-01-05T15:12:24.489196Z"
  },
  {
    "symbol": "KBANK",
    "name": "KBANK",
    "price": 150.11,
    "change_24h": -1.57,
    "volume_24h": 4012658,
    "high_24h": 152.36,
    "low_24h": 147.86,
    "rsi": 46.82,
    "macd": {
      "macd": -0.2269,
      "signal": -0.034,
      "histogram": -0.1928
    },
    "signal": "HOLD",
    "strength": 0.22,
    "sector": "Banking",
    "timestamp": "2026-01-05T15:12:24.489260Z"
  },
  {
    "symbol": "SCB",
    "name": "SCB",
    "price": 96.83,
    "change_24h": 1.12,
    "volume_24h": 5867203,
    "high_24h": 98.28,
    "low_24h": 95.37,
    "rsi": 55.41,
    "macd": {
      "macd": 0.4465,
      "signal": 0.067,
      "histogram": 0.3795
    },
    "signal": "HOLD",
    "strength": 0.22,
    "sector": "Banking",
    "timestamp": "2026-01-05T15:12:24.489306Z"
  },
  {
    "symbol": "BBL",
    "name": "BBL",
    "price": 172.64,
    "change_24h": 2.46,
    "volume_24h": 2379846,
    "high_24h": 175.23,
    "low_24h": 170.05,
    "rsi": 51.05,
    "macd": {
      "macd": 0.1985,
      "signal": 0.0298,
      "histogram": 0.1687
    },
    "signal": "HOLD",
    "strength": 0.27,
    "sector": "Banking",
    "timestamp": "2026-01-05T15:12:24.489345Z"
  },
  {
    "symbol": "GULF",
    "name": "GULF",
    "price": 42.86,
    "change_24h": -5.29,
    "volume_24h": 20186692,
    "high_24h": 43.5,
    "low_24h": 42.22,
    "rsi": 36.49,
    "macd": {
      "macd": -0.1053,
      "signal": -0.0158,
      "histogram": -0.0895
    },
    "signal": "HOLD",
    "strength": 0.8,
    "sector": "Energy",
    "timestamp": "2026-01-05T15:12:24.489381Z"
  },
  {
    "symbol": "PTTEP",
    "name": "PTTEP",
    "price": 134.44,
    "change_24h": -0.42,
    "volume_24h": 4241633,
    "high_24h": 136.45,
    "low_24h": 132.42,
    "rsi": 44.46,
    "macd": {
      "macd": 0.134,
      "signal": 0.0201,
      "histogram": 0.1139
    },
    "signal": "HOLD",
    "strength": 0.15,
    "sector": "Energy",
    "timestamp": "2026-01-05T15:12:24.489417Z"
  },
  {
    "symbol": "BDMS",
    "name": "BDMS",
    "price": 29.36,
    "change_24h": 2.14,
    "volume_24h": 18392331,
    "high_24h": 29.8,
    "low_24h": 28.92,
    "rsi": 54.89,
    "macd": {
      "macd": 0.1364,
      "signal": 0.0205,
      "histogram": 0.116
    },
    "signal": "HOLD",
    "strength": 0.31,
    "sector": "Healthcare",
    "timestamp": "2026-01-05T15:12:24.489452Z"
  },
  {
    "symbol": "TRUE",
    "name": "TRUE",
    "price": 9.86,
    "change_24h": -4.24,
    "volume_24h": 50952707,
    "high_24h": 10.01,
    "low_24h": 9.72,
    "rsi": 47.45,
    "macd": {
      "macd": -0.0639,
      "signal": -0.0096,
      "histogram": -0.0543
    },
    "signal": "SELL",
    "strength": 0.48,
    "sector": "Telecom",
    "timestamp": "2026-01-05T15:12:24.489489Z"
  },
  {
    "symbol": "BEM",
    "name": "BEM",
    "price": 8.68,
    "change_24h": 1.47,
    "volume_24h": 96351520,
    "high_24h": 8.81,
    "low_24h": 8.55,
    "rsi": 53.84,
    "macd": {
      "macd": 0.0187,
      "signal": 0.0028,
      "histogram": 0.0159
    },
    "signal": "HOLD",
    "strength": 0.22,
    "sector": "Transport",
    "timestamp": "2026-01-05T15:12:24.489526Z"
  },
  {
    "symbol": "MINT",
    "name": "MINT",
    "price": 30.61,
    "change_24h": -4.34,
    "volume_24h": 17091668,
    "high_24h": 31.07,
    "low_24h": 30.15,
    "rsi": 47.4,
    "macd": {
      "macd": -0.1488,
      "signal": -0.0223,
      "histogram": -0.1265
    },
    "signal": "SELL",
    "strength": 0.49,
    "sector": "Food",
    "timestamp": "2026-01-05T15:12:24.489581Z"
  },
  {
    "symbol": "CPN",
    "name": "CPN",
    "price": 55.96,
    "change_24h": -4.34,
    "volume_24h": 14469396,
    "high_24h": 56.8,
    "low_24h": 55.12,
    "rsi": 46.7,
    "macd": {
      "macd": -0.1162,
      "signal": -0.0174,
      "histogram": -0.0988
    },
    "signal": "SELL",
    "strength": 0.5,
    "sector": "Property",
    "timestamp": "2026-01-05T15:12:24.489620Z"
  },
  {
    "symbol": "DELTA",
    "name": "DELTA",
    "price": 89.95,
    "change_24h": 0.78,
    "volume_24h": 3195036,
    "high_24h": 91.3,
    "low_24h": 88.6,
    "rsi": 58.66,
    "macd": {
      "macd": -0.0011,
      "signal": -0.0002,
      "histogram": -0.001
    },
    "signal": "HOLD",
    "strength": 0.25,
    "sector": "Electronics",
    "timestamp": "2026-01-05T15:12:24.489661Z"
  },
  {
    "symbol": "EA",
    "name": "EA",
    "price": 18.55,
    "change_24h": -0.81,
    "volume_24h": 52131537,
    "high_24h": 18.83,
    "low_24h": 18.27,
    "rsi": 53.55,
    "macd": {
      "macd": -0.0609,
      "signal": -0.0091,
      "histogram": -0.0517
    },
    "signal": "HOLD",
    "strength": 0.15,
    "sector": "Energy",
    "timestamp": "2026-01-05T15:12:24.489696Z"
  },
  {
    "symbol": "GPSC",
    "name": "GPSC",
    "price": 59.47,
    "change_24h": 2.54,
    "volume_24h": 5511861,
    "high_24h": 60.36,
    "low_24h": 58.58,
    "rsi": 50.98,
    "macd": {
      "macd": 0.0216,
      "signal": 0.0032,
      "histogram": 0.0183
    },
    "signal": "HOLD",
    "strength": 0.27,
    "sector": "Energy",
    "timestamp": "2026-01-05T15:12:24.489728Z"
  },
  {
    "symbol": "INTUCH",
    "name": "INTUCH",
    "price": 84.31,
    "change_24h": -0.81,
    "volume_24h": 5725607,
    "high_24h": 85.57,
    "low_24h": 83.04,
    "rsi": 47.23,
    "macd": {
      "macd": -0.304,
      "signal": -0.0456,
      "histogram": -0.2584
    },
    "signal": "HOLD",
    "strength": 0.14,
    "sector": "Telecom",
    "timestamp": "2026-01-05T15:12:24.489760Z"
  },
  {
    "symbol": "IVL",
    "name": "IVL",
    "price": 30.68,
    "change_24h": -4.87,
    "volume_24h": 11642426,
    "high_24h": 31.14,
    "low_24h": 30.22,
    "rsi": 46.08,
    "macd": {
      "macd": -0.0809,
      "signal": -0.0121,
      "histogram": -0.0688
    },
    "signal": "SELL",
    "strength": 0.57,
    "sector": "Petrochemical",
    "timestamp": "2026-01-05T15:12:24.489796Z"
  },
  {
    "symbol": "KCE",
    "name": "KCE",
    "price": 44.21,
    "change_24h": -1.76,
    "volume_24h": 18803548,
    "high_24h": 44.87,
    "low_24h": 43.55,
    "rsi": 43.15,
    "macd": {
      "macd": -0.115,
      "signal": -0.0172,
      "histogram": -0.0977
    },
    "signal": "HOLD",
    "strength": 0.31,
    "sector": "Electronics",
    "timestamp": "2026-01-05T15:12:24.489833Z"
  },
  {
    "symbol": "KTB",
    "name": "KTB",
    "price": 23.44,
    "change_24h": 2.82,
    "volume_24h": 11671647,
    "high_24h": 23.8,
    "low_24h": 23.09,
    "rsi": 57.22,
    "macd": {
      "macd": 0.082,
      "signal": 0.0123,
      "histogram": 0.0697
    },
    "signal": "HOLD",
    "strength": 0.43,
    "sector": "Banking",
    "timestamp": "2026-01-05T15:12:24.489871Z"
  },
  {
    "symbol": "BANPU",
    "name": "BANPU",
    "price": 8.77,
    "change_24h": 6.28,
    "volume_24h": 38120342,
    "high_24h": 8.9,
    "low_24h": 8.64,
    "rsi": 54.67,
    "macd": {
      "macd": 0.0276,
      "signal": 0.0041,
      "histogram": 0.0234
    },
    "signal": "BUY",
    "strength": 0.72,
    "sector": "Energy",
    "timestamp": "2026-01-05T15:12:24.489909Z"
  },
  {
    "symbol": "BCP",
    "name": "BCP",
    "price": 26.48,
    "change_24h": -5.43,
    "volume_24h": 27475816,
    "high_24h": 26.88,
    "low_24h": 26.08,
    "rsi": 38.19,
    "macd": {
      "macd": -0.005,
      "signal": -0.0007,
      "histogram": -0.0042
    },
    "signal": "HOLD",
    "strength": 0.78,
    "sector": "Energy",
    "timestamp": "2026-01-05T15:12:24.489944Z"
  },
  {
    "symbol": "BH",
    "name": "BH",
    "price": 151.61,
    "change_24h": 4.56,
    "volume_24h": 6270448,
    "high_24h": 153.88,
    "low_24h": 149.34,
    "rsi": 58.09,
    "macd": {
      "macd": 0.642,
      "signal": 0.0963,
      "histogram": 0.5457
    },
    "signal": "BUY",
    "strength": 0.62,
    "sector": "Healthcare",
    "timestamp": "2026-01-05T15:12:24.489980Z"
  },
  {
    "symbol": "BJC",
    "name": "BJC",
    "price": 30.47,
    "change_24h": -3.27,
    "volume_24h": 15161497,
    "high_24h": 30.93,
    "low_24h": 30.01,
    "rsi": 49.55,
    "macd": {
      "macd": 0.0591,
      "signal": 0.0089,
      "histogram": 0.0502
    },
    "signal": "HOLD",
    "strength": 0.34,
    "sector": "Commerce",
    "timestamp": "2026-01-05T15:12:24.490017Z"
  },
  {
    "symbol": "BTS",
    "name": "BTS",
    "price": 6.38,
    "change_24h": 1.26,
    "volume_24h": 68113371,
    "high_24h": 6.48,
    "low_24h": 6.28,
    "rsi": 47.58,
    "macd": {
      "macd": 0.0263,
      "signal": 0.0039,
      "histogram": 0.0224
    },
    "signal": "HOLD",
    "strength": 0.17,
    "sector": "Transport",
    "timestamp": "2026-01-05T15:12:24.490053Z"
  },
  {
    "symbol": "CBG",
    "name": "CBG",
    "price": 131.4,
    "change_24h": 2.25,
    "volume_24h": 3128533,
    "high_24h": 133.37,
    "low_24h": 129.43,
    "rsi": 50.28,
    "macd": {
      "macd": -0.0868,
      "signal": -0.013,
      "histogram": -0.0738
    },
    "signal": "HOLD",
    "strength": 0.23,
    "sector": "Food",
    "timestamp": "2026-01-05T15:12:24.490088Z"
  },
  {
    "symbol": "CENTEL",
    "name": "CENTEL",
    "price": 36.84,
    "change_24h": -4.32,
    "volume_24h": 13870491,
    "high_24h": 37.39,
    "low_24h": 36.28,
    "rsi": 43.0,
    "macd": {
      "macd": -0.032,
      "signal": -0.0048,
      "histogram": -0.0272
    },
    "signal": "SELL",
    "strength": 0.57,
    "sector": "Hotel",
    "timestamp": "2026-01-05T15:12:24.490124Z"
  },
  {
    "symbol": "COM7",
    "name": "COM7",
    "price": 27.99,
    "change_24h": -2.63,
    "volume_24h": 15490898,
    "high_24h": 28.41,
    "low_24h": 27.57,
    "rsi": 43.1,
    "macd": {
      "macd": -0.113,
      "signal": -0.017,
      "histogram": -0.0961
    },
    "signal": "HOLD",
    "strength": 0.4,
    "sector": "Commerce",
    "timestamp": "2026-01-05T15:12:24.490166Z"
  },
  {
    "symbol": "CRC",
    "name": "CRC",
    "price": 34.67,
    "change_24h": -0.94,
    "volume_24h": 19409698,
    "high_24h": 35.19,
    "low_24h": 34.15,
    "rsi": 53.24,
    "macd": {
      "macd": -0.1251,
      "signal": -0.0188,
      "histogram": -0.1063
    },
    "signal": "HOLD",
    "strength": 0.16,
    "sector": "Commerce",
    "timestamp": "2026-01-05T15:12:24.490204Z"
  },
  {
    "symbol": "EGCO",
    "name": "EGCO",
    "price": 158.59,
    "change_24h": 0.37,
    "volume_24h": 3359482,
    "high_24h": 160.97,
    "low_24h": 156.21,
    "rsi": 50.67,
    "macd": {
      "macd": 0.0515,
      "signal": 0.0077,
      "histogram": 0.0438
    },
    "signal": "HOLD",
    "strength": 0.05,
    "sector": "Energy",
    "timestamp": "2026-01-05T15:12:24.490240Z"
  },
  {
    "symbol": "GLOBAL",
    "name": "GLOBAL",
    "price": 17.47,
    "change_24h": -3.99,
    "volume_24h": 21656447,
    "high_24h": 17.74,
    "low_24h": 17.21,
    "rsi": 44.08,
    "macd": {
      "macd": -0.0776,
      "signal": -0.0116,
      "histogram": -0.066
    },
    "signal": "SELL",
    "strength": 0.52,
    "sector": "Food",
    "timestamp": "2026-01-05T15:12:24.490277Z"
  },
  {
    "symbol": "HMPRO",
    "name": "HMPRO",
    "price": 14.85,
    "change_24h": 1.69,
    "volume_24h": 47950220,
    "high_24h": 15.07,
    "low_24h": 14.62,
    "rsi": 57.35,
    "macd": {
      "macd": 0.0524,
      "signal": 0.0079,
      "histogram": 0.0445
    },
    "signal": "HOLD",
    "strength": 0.32,
    "sector": "Commerce",
    "timestamp": "2026-01-05T15:12:24.490315Z"
  },
  {
    "symbol": "IRPC",
    "name": "IRPC",
    "price": 3.52,
    "change_24h": 3.0,
    "volume_24h": 192392190,
    "high_24h": 3.58,
    "low_24h": 3.47,
    "rsi": 57.88,
    "macd": {
      "macd": 0.0055,
      "signal": 0.0008,
      "histogram": 0.0047
    },
    "signal": "HOLD",
    "strength": 0.46,
    "sector": "Petrochemical",
    "timestamp": "2026-01-05T15:12:24.490353Z"
  },
  {
    "symbol": "JMT",
    "name": "JMT",
    "price": 22.1,
    "change_24h": -0.0,
    "volume_24h": 20559763,
    "high_24h": 22.43,
    "low_24h": 21.77,
    "rsi": 47.99,
    "macd": {
      "macd": -0.0433,
      "signal": -0.0065,
      "histogram": -0.0368
    },
    "signal": "HOLD",
    "strength": 0.04,
    "sector": "Finance",
    "timestamp": "2026-01-05T15:12:24.490392Z"
  },
  {
    "symbol": "JMART",
    "name": "JMART",
    "price": 16.14,
    "change_24h": 2.14,
    "volume_24h": 20262670,
    "high_24h": 16.38,
    "low_24h": 15.9,
    "rsi": 49.41,
    "macd": {
      "macd": 0.0284,
      "signal": 0.0043,
      "histogram": 0.0241
    },
    "signal": "HOLD",
    "strength": 0.23,
    "sector": "Commerce",
    "timestamp": "2026-01-05T15:12:24.490430Z"
  },
  {
    "symbol": "TIDLOR",
    "name": "TIDLOR",
    "price": 18.02,
    "change_24h": -2.62,
    "volume_24h": 29554865,
    "high_24h": 18.29,
    "low_24h": 17.75,
    "rsi": 47.31,
    "macd": {
      "macd": 0.0052,
      "signal": 0.0008,
      "histogram": 0.0044
    },
    "signal": "HOLD",
    "strength": 0.32,
    "sector": "Finance",
    "timestamp": "2026-01-05T15:12:24.490466Z"
  },
  {
    "symbol": "TTB",
    "name": "TTB",
    "price": 1.84,
    "change_24h": 3.5,
    "volume_24h": 438686909,
    "high_24h": 1.87,
    "low_24h": 1.81,
    "rsi": 53.03,
    "macd": {
      "macd": 0.0111,
      "signal": 0.0017,
      "histogram": 0.0094
    },
    "signal": "BUY",
    "strength": 0.41,
    "sector": "Banking",
    "timestamp": "2026-01-05T15:12:24.490510Z"
  },
  {
    "symbol": "TU",
    "name": "TU",
    "price": 15.23,
    "change_24h": 1.54,
    "volume_24h": 27638801,
    "high_24h": 15.46,
    "low_24h": 15.0,
    "rsi": 65.09,
    "macd": {
      "macd": 0.0136,
      "signal": 0.002,
      "histogram": 0.0116
    },
    "signal": "HOLD",
    "strength": 0.46,
    "sector": "Food",
    "timestamp": "2026-01-05T15:12:24.490567Z"
  },
  {
    "symbol": "WHA",
    "name": "WHA",
    "price": 4.68,
    "change_24h": 2.55,
    "volume_24h": 74092314,
    "high_24h": 4.75,
    "low_24h": 4.61,
    "rsi": 57.41,
    "macd": {
      "macd": 0.0161,
      "signal": 0.0024,
      "histogram": 0.0137
    },
    "signal": "HOLD",
    "strength": 0.4,
    "sector": "Property",
    "timestamp": "2026-01-05T15:12:24.490606Z"
  },
  {
    "symbol": "OR",
    "name": "OR",
    "price": 17.73,
    "change_24h": -3.1,
    "volume_24h": 29042542,
    "high_24h": 18.0,
    "low_24h": 17.47,
    "rsi": 41.92,
    "macd": {
      "macd": -0.102,
      "signal": -0.0153,
      "histogram": -0.0867
    },
    "signal": "SELL",
    "strength": 0.47,
    "sector": "Energy",
    "timestamp": "2026-01-05T15:12:24.490646Z"
  },
  {
    "symbol": "AWC",
    "name": "AWC",
    "price": 4.91,
    "change_24h": 1.82,
    "volume_24h": 95010750,
    "high_24h": 4.98,
    "low_24h": 4.83,
    "rsi": 52.77,
    "macd": {
      "macd": -0.0138,
      "signal": -0.0021,
      "histogram": -0.0117
    },
    "signal": "HOLD",
    "strength": 0.24,
    "sector": "Property",
    "timestamp": "2026-01-05T15:12:24.490684Z"
  },
  {
    "symbol": "OSP",
    "name": "OSP",
    "price": 23.7,
    "change_24h": -3.26,
    "volume_24h": 23506270,
    "high_24h": 24.06,
    "low_24h": 23.34,
    "rsi": 45.59,
    "macd": {
      "macd": 0.0094,
      "signal": 0.0014,
      "histogram": 0.008
    },
    "signal": "HOLD",
    "strength": 0.41,
    "sector": "Commerce",
    "timestamp": "2026-01-05T15:12:24.490722Z"
  },
  {
    "symbol": "SAWAD",
    "name": "SAWAD",
    "price": 40.76,
    "change_24h": -3.52,
    "volume_24h": 11326392,
    "high_24h": 41.38,
    "low_24h": 40.15,
    "rsi": 42.21,
    "macd": {
      "macd": 0.013,
      "signal": 0.0019,
      "histogram": 0.011
    },
    "signal": "HOLD",
    "strength": 0.51,
    "sector": "Finance",
    "timestamp": "2026-01-05T15:12:24.490755Z"
  },
  {
    "symbol": "STGT",
    "name": "STGT",
    "price": 11.4,
    "change_24h": 1.78,
    "volume_24h": 30368028,
    "high_24h": 11.57,
    "low_24h": 11.23,
    "rsi": 58.99,
    "macd": {
      "macd": -0.0078,
      "signal": -0.0012,
      "histogram": -0.0066
    },
    "signal": "HOLD",
    "strength": 0.36,
    "sector": "Rubber",
    "timestamp": "2026-01-05T15:12:24.490785Z"
  },
  {
    "symbol": "TISCO",
    "name": "TISCO",
    "price": 103.4,
    "change_24h": 4.97,
    "volume_24h": 3108546,
    "high_24h": 104.95,
    "low_24h": 101.85,
    "rsi": 53.31,
    "macd": {
      "macd": 0.2802,
      "signal": 0.042,
      "histogram": 0.2382
    },
    "signal": "BUY",
    "strength": 0.56,
    "sector": "Banking",
    "timestamp": "2026-01-05T15:12:24.490817Z"
  },
  {
    "symbol": "TOP",
    "name": "TOP",
    "price": 41.93,
    "change_24h": -1.92,
    "volume_24h": 14056947,
    "high_24h": 42.56,
    "low_24h": 41.3,
    "rsi": 47.34,
    "macd": {
      "macd": -0.1543,
      "signal": -0.0231,
      "histogram": -0.1312
    },
    "signal": "HOLD",
    "strength": 0.24,
    "sector": "Energy",
    "timestamp": "2026-01-05T15:12:24.490854Z"
  },
  {
    "symbol": "MTC",
    "name": "MTC",
    "price": 43.89,
    "change_24h": 4.5,
    "volume_24h": 20270561,
    "high_24h": 44.55,
    "low_24h": 43.23,
    "rsi": 52.44,
    "macd": {
      "macd": 0.1746,
      "signal": 0.0262,
      "histogram": 0.1484
    },
    "signal": "BUY",
    "strength": 0.5,
    "sector": "Finance",
    "timestamp": "2026-01-05T15:12:24.490885Z"
  }
]